yaml_resume/__init__.py
yaml_resume/__main__.py
yaml_resume/cli.py
yaml_resume/resume/__init__.py
yaml_resume/resume/contact.py
yaml_resume/resume/degree.py
yaml_resume/resume/experience.py
yaml_resume/resume/hobby.py
yaml_resume/resume/language.py
yaml_resume/resume/profile.py
yaml_resume/resume/project.py
yaml_resume/resume/skill.py
yaml_resume/templates/classic.css
yaml_resume/templates/classic.html
yaml_resume/templates/material.css
yaml_resume/templates/material.html
yaml_resume/validator/__init__.py
yaml_resume/validator/schema.py
yaml_resume-0.7.10.dist-info/LICENSE
yaml_resume-0.7.10.dist-info/METADATA
yaml_resume-0.7.10.dist-info/WHEEL
yaml_resume-0.7.10.dist-info/entry_points.txt
yaml_resume-0.7.10.dist-info/top_level.txt
yaml_resume-0.7.10.dist-info/RECORD
