Metadata-Version: 2.1
Name: yaml-resume
Version: 0.7.10
Summary: Command line interface to build/validate YAML resumes
Home-page: https://github.com/notsag/yaml-resume
Author: Maxime GASTON
Author-email: maxime@gaston.sh
License: gpl-3.0
Keywords: resume,yaml
Platform: UNKNOWN
Classifier: Development Status :: 3 - Alpha
Classifier: Intended Audience :: Developers
Classifier: Intended Audience :: Education
Classifier: Intended Audience :: Information Technology
Classifier: License :: OSI Approved :: GNU General Public License v3 (GPLv3)
Classifier: Operating System :: OS Independent
Classifier: Programming Language :: Python
Classifier: Programming Language :: Python :: 3
Classifier: Programming Language :: Python :: 3.5
Classifier: Programming Language :: Python :: 3.6
Classifier: Programming Language :: Python :: 3.7
Classifier: Programming Language :: Python :: 3.8
Requires-Python: >=3
